setup.py
utime.py
pycopy_cpython_utime.egg-info/PKG-INFO
pycopy_cpython_utime.egg-info/SOURCES.txt
pycopy_cpython_utime.egg-info/dependency_links.txt
pycopy_cpython_utime.egg-info/top_level.txt